setup.py
improve/algorithm.py
improve/calibration.py
improve/define.py
improve/improve.ui
improve/interface.py
improve/release_note.txt
improve/version.py
ls2_picture.egg-info/PKG-INFO
ls2_picture.egg-info/SOURCES.txt
ls2_picture.egg-info/dependency_links.txt
ls2_picture.egg-info/entry_points.txt
ls2_picture.egg-info/top_level.txt