Metadata-Version: 1.0
Name: ls2-picture
Version: 1.0.0
Summary: Look spot II picture improvement
Home-page: https://github.com/gxfca/gitTest
Author: Laipac
Author-email: feng.gao@laipac.com
License: UNKNOWN
Platform: UNKNOWN
